<annotation>
	<folder>Wooden Utensils</folder>
	<filename>10010.jpg</filename>
	<path>C:\Users\User\Downloads\Final Images\Biodegradeable\Wooden Utensils\10010.jpg</path>
	<source>
		<database>Unknown</database>
	</source>
	<size>
		<width>612</width>
		<height>394</height>
		<depth>3</depth>
	</size>
	<segmented>0</segmented>
	<object>
		<name>Wooden Utensils</name>
		<pose>Unspecified</pose>
		<truncated>0</truncated>
		<difficult>0</difficult>
		<bndbox>
			<xmin>44</xmin>
			<ymin>114</ymin>
			<xmax>527</xmax>
			<ymax>302</ymax>
		</bndbox>
	</object>
</annotation>
